aiida_graphql/__init__.py
aiida_graphql/api/computer.py
aiida_graphql/api/node.py
aiida_graphql/api/user.py
aiida_graphql/schema.py
aiida_graphql-0.0.2.dist-info/LICENSE
aiida_graphql-0.0.2.dist-info/WHEEL
aiida_graphql-0.0.2.dist-info/METADATA
aiida_graphql-0.0.2.dist-info/RECORD
