Metadata-Version: 2.1
Name: aiida-graphql
Version: 0.0.2
Summary: Strawberry-based GraphQL API Server for AiiDA
Home-page: https://github.com/dev-zero/aiida-graphql
License: MIT
Author: Tiziano Müller
Author-email: tiziano.mueller@chem.uzh.ch
Requires-Python: >=3.7,<4.0
Classifier: Development Status :: 3 - Alpha
Classifier: Intended Audience :: Science/Research
Classifier: License :: OSI Approved :: MIT License
Classifier: Operating System :: OS Independent
Classifier: Programming Language :: Python :: 3
Classifier: Programming Language :: Python :: 3.7
Classifier: Programming Language :: Python :: 3.8
Classifier: Topic :: Software Development :: Libraries :: Python Modules
Requires-Dist: aiida (>=1.0.0b6,<2.0.0)
Requires-Dist: strawberry-graphql (>=0.16.7,<0.17.0)
Project-URL: Repository, https://github.com/dev-zero/aiida-graphql
